pymel/__init__.py
pymel/all.py
pymel/all.pyi
pymel/api/__init__.py
pymel/api/allapi.py
pymel/api/plugins.py
pymel/cache/mayaApi2019.py
pymel/cache/mayaApi2020.py
pymel/cache/mayaApi2022.py
pymel/cache/mayaApi2023.py
pymel/cache/mayaApiMelBridge.py
pymel/cache/mayaCmdsDocs2019.py
pymel/cache/mayaCmdsDocs2020.py
pymel/cache/mayaCmdsDocs2022.py
pymel/cache/mayaCmdsDocs2023.py
pymel/cache/mayaCmdsExamples2019.py
pymel/cache/mayaCmdsExamples2020.py
pymel/cache/mayaCmdsExamples2022.py
pymel/cache/mayaCmdsExamples2023.py
pymel/cache/mayaCmdsList2019.py
pymel/cache/mayaCmdsList2020.py
pymel/cache/mayaCmdsList2022.py
pymel/cache/mayaCmdsList2023.py
pymel/core/__init__.py
pymel/core/__init__.pyi
pymel/core/animation.py
pymel/core/animation.pyi
pymel/core/context.py
pymel/core/context.pyi
pymel/core/datatypes.py
pymel/core/datatypes.pyi
pymel/core/effects.py
pymel/core/effects.pyi
pymel/core/general.py
pymel/core/general.pyi
pymel/core/language.py
pymel/core/language.pyi
pymel/core/modeling.py
pymel/core/modeling.pyi
pymel/core/nodetypes.py
pymel/core/nodetypes.pyi
pymel/core/other.py
pymel/core/other.pyi
pymel/core/rendering.py
pymel/core/rendering.pyi
pymel/core/runtime.py
pymel/core/runtime.pyi
pymel/core/system.py
pymel/core/system.pyi
pymel/core/uitypes.py
pymel/core/uitypes.pyi
pymel/core/windows.py
pymel/core/windows.pyi
pymel/internal/__init__.py
pymel/internal/__init__.pyi
pymel/internal/apicache.py
pymel/internal/apicache.pyi
pymel/internal/cachebase.py
pymel/internal/cachebase.pyi
pymel/internal/cmdcache.py
pymel/internal/cmdcache.pyi
pymel/internal/docstrings.py
pymel/internal/docstrings.pyi
pymel/internal/factories.py
pymel/internal/factories.pyi
pymel/internal/parsers.py
pymel/internal/parsers.pyi
pymel/internal/plogging.py
pymel/internal/plogging.pyi
pymel/internal/pmcmds.py
pymel/internal/pmcmds.pyi
pymel/internal/pwarnings.py
pymel/internal/pwarnings.pyi
pymel/internal/startup.py
pymel/internal/startup.pyi
pymel/mayautils.py
pymel/mayautils.pyi
pymel/py.typed
pymel-1.3.1.dist-info/LICENSE
pymel-1.3.1.dist-info/METADATA
pymel-1.3.1.dist-info/WHEEL
pymel-1.3.1.dist-info/entry_points.txt
pymel-1.3.1.dist-info/RECORD
