Metadata-Version: 2.1
Name: pymel
Version: 1.3.1
Summary: Python in Maya Done Right
Home-page: https://github.com/Lumapictures/pymel
License: BSD
Keywords: maya,mel,3d,graphics,games,VFX,CG,animation
Author: Chad Dombrova
Requires-Python: >=2.7, !=3.0.*, !=3.1.*, !=3.2.*, !=3.3.*, !=3.4.*, !=3.5.*, !=3.6.*
Classifier: License :: Other/Proprietary License
Classifier: Programming Language :: Python :: 2
Classifier: Programming Language :: Python :: 2.7
Classifier: Programming Language :: Python :: 3
Classifier: Programming Language :: Python :: 3.7
Classifier: Programming Language :: Python :: 3.8
Classifier: Programming Language :: Python :: 3.9
Classifier: Programming Language :: Python :: 3.10
Classifier: Programming Language :: Python :: 3.11
Requires-Dist: future (>=0.18)
Project-URL: Repository, https://github.com/Lumapictures/pymel
